README.rst
setup.cfg
setup.py
pyramid_pystache/__init__.py
pyramid_pystache/interfaces.py
pyramid_pystache/mustache.py
pyramid_pystache/renderer.py
pyramid_pystache.egg-info/PKG-INFO
pyramid_pystache.egg-info/SOURCES.txt
pyramid_pystache.egg-info/dependency_links.txt
pyramid_pystache.egg-info/entry_points.txt
pyramid_pystache.egg-info/not-zip-safe
pyramid_pystache.egg-info/requires.txt
pyramid_pystache.egg-info/top_level.txt
pyramid_pystache/tests/__init__.py
pyramid_pystache/tests/test_mustache.py
pyramid_pystache/tests/test_renderers.py