Metadata-Version: 1.1
Name: pyramid-pystache
Version: 0.2
Summary: Mustache template bindings using Pystache for the Pyramid web framework
Home-page: https://github.com/darrenlucas/pyramid_pystache
Author: Darren Lucas
Author-email: me@darrenlucas.com
License: BSD-derived (http://www.repoze.org/LICENSE.txt)
Platform: UNKNOWN
Classifier: Programming Language :: Python
Classifier: Framework :: Pylons
Classifier: Programming Language :: Python :: 2.6
Classifier: Programming Language :: Python :: 2.7
Classifier: Programming Language :: Python :: 3
Classifier: Programming Language :: Python :: 3.2
Classifier: Programming Language :: Python :: 3.3
Classifier: Programming Language :: Python :: 3.4
Classifier: Intended Audience :: Developers
Classifier: License :: Repoze Public License
Classifier: Topic :: Text Processing :: Markup :: HTML
